{"textures":{"0":"modelengine:entity/tupandactylus"},"elements":[{"from":[7.532897,7.142857,7.0132],"to":[11.532897,8.857143,8.727486],"rotation":{"angle":0.0,"axis":"y","origin":[6.39004,1.7142854,9.298914]},"faces":{"east":{"uv":[2.125,9.5,1.75,9.875],"rotation":0,"texture":"#0","tintindex":0},"south":{"uv":[9.125,3.375,8.25,3.75],"rotation":0,"texture":"#0","tintindex":0},"north":{"uv":[9.125,3.0,8.25,3.375],"rotation":0,"texture":"#0","tintindex":0},"west":{"uv":[9.875,1.625,9.5,2.0],"rotation":0,"texture":"#0","tintindex":0},"up":{"uv":[8.25,4.125,9.125,3.75],"rotation":0,"texture":"#0","tintindex":0},"down":{"uv":[8.25,4.125,9.125,4.5],"rotation":0,"texture":"#0","tintindex":0}}},{"from":[7.532897,8.0,3.584628],"to":[17.247183,8.0,11.0132],"rotation":{"angle":0.0,"axis":"y","origin":[6.39004,1.7142854,9.298914]},"faces":{"east":{"uv":[1.625,0.0,0.0,0.0],"rotation":0,"texture":"#0","tintindex":0},"south":{"uv":[2.125,0.0,0.0,0.0],"rotation":0,"texture":"#0","tintindex":0},"north":{"uv":[2.125,0.0,0.0,0.0],"rotation":0,"texture":"#0","tintindex":0},"west":{"uv":[1.625,0.0,0.0,0.0],"rotation":0,"texture":"#0","tintindex":0},"up":{"uv":[5.5,6.125,7.625,4.5],"rotation":0,"texture":"#0","tintindex":0},"down":{"uv":[5.5,4.5,7.625,6.125],"rotation":0,"texture":"#0","tintindex":0}}},{"from":[14.72428,7.428571,1.8559084],"to":[15.867138,8.571428,8.713052],"rotation":{"angle":-45.0,"axis":"y","origin":[14.544314,8.0,3.8722801]},"faces":{"east":{"uv":[9.75,2.5,8.25,2.75],"rotation":0,"texture":"#0","tintindex":0},"south":{"uv":[3.75,9.75,3.5,10.0],"rotation":0,"texture":"#0","tintindex":0},"north":{"uv":[7.25,9.0,7.0,9.25],"rotation":0,"texture":"#0","tintindex":0},"west":{"uv":[9.75,2.25,8.25,2.5],"rotation":0,"texture":"#0","tintindex":0},"up":{"uv":[4.75,9.375,5.0,7.875],"rotation":0,"texture":"#0","tintindex":0},"down":{"uv":[5.0,7.875,5.25,9.375],"rotation":0,"texture":"#0","tintindex":0}}}],"display":{"head":{"translation":[0.0,-6.4,0.0],"scale":[4.0,4.0,4.0]}}}