{"textures":{"0":"modelengine:entity/pet_spawner"},"elements":[{"from":[6.857143,8.714438,9.599614],"to":[7.714286,9.74301,11.171042],"rotation":{"angle":-22.5,"axis":"x","origin":[10.428572,11.093566,10.512524]},"faces":{"east":{"uv":[5.75,7.5,6.5,8.0],"rotation":0,"texture":"#0","tintindex":0},"south":{"uv":[5.5,8.0,6.0,8.5],"rotation":0,"texture":"#0","tintindex":0},"north":{"uv":[8.0,3.5,8.5,4.0],"rotation":0,"texture":"#0","tintindex":0},"west":{"uv":[6.5,7.5,7.25,8.0],"rotation":0,"texture":"#0","tintindex":0},"up":{"uv":[8.0,7.75,7.5,7.0],"rotation":0,"texture":"#0","tintindex":0},"down":{"uv":[8.25,0.0,7.75,0.75],"rotation":0,"texture":"#0","tintindex":0}}},{"from":[6.428571,7.736423,7.798238],"to":[8.142858,9.450708,11.2268095],"rotation":{"angle":-22.5,"axis":"x","origin":[7.285714,8.022138,9.512524]},"faces":{"east":{"uv":[6.0,3.25,7.5,4.0],"rotation":0,"texture":"#0","tintindex":0},"south":{"uv":[7.5,2.25,8.25,3.0],"rotation":0,"texture":"#0","tintindex":0},"north":{"uv":[1.25,7.5,2.0,8.25],"rotation":0,"texture":"#0","tintindex":0},"west":{"uv":[6.75,1.0,8.25,1.75],"rotation":0,"texture":"#0","tintindex":0},"up":{"uv":[3.25,8.25,2.5,6.75],"rotation":0,"texture":"#0","tintindex":0},"down":{"uv":[4.0,6.75,3.25,8.25],"rotation":0,"texture":"#0","tintindex":0}}},{"from":[6.5714283,7.87928,11.2268095],"to":[6.857143,9.307852,12.369667],"rotation":{"angle":-22.5,"axis":"x","origin":[7.285714,8.022138,9.512524]},"faces":{"east":{"uv":[4.0,7.75,4.5,8.5],"rotation":0,"texture":"#0","tintindex":0},"south":{"uv":[2.5,8.25,2.75,9.0],"rotation":0,"texture":"#0","tintindex":0},"north":{"uv":[8.25,2.25,8.5,3.0],"rotation":0,"texture":"#0","tintindex":0},"west":{"uv":[4.5,7.75,5.0,8.5],"rotation":0,"texture":"#0","tintindex":0},"up":{"uv":[3.0,8.75,2.75,8.25],"rotation":0,"texture":"#0","tintindex":0},"down":{"uv":[3.25,8.25,3.0,8.75],"rotation":0,"texture":"#0","tintindex":0}}},{"from":[7.714286,7.87928,11.2268095],"to":[8.0,9.307852,12.369667],"rotation":{"angle":-22.5,"axis":"x","origin":[13.571428,8.022138,9.512524]},"faces":{"east":{"uv":[5.0,7.75,4.5,8.5],"rotation":0,"texture":"#0","tintindex":0},"south":{"uv":[2.75,8.25,2.5,9.0],"rotation":0,"texture":"#0","tintindex":0},"north":{"uv":[8.5,2.25,8.25,3.0],"rotation":0,"texture":"#0","tintindex":0},"west":{"uv":[4.5,7.75,4.0,8.5],"rotation":0,"texture":"#0","tintindex":0},"up":{"uv":[2.75,8.75,3.0,8.25],"rotation":0,"texture":"#0","tintindex":0},"down":{"uv":[3.0,8.25,3.25,8.75],"rotation":0,"texture":"#0","tintindex":0}}}],"display":{"head":{"translation":[0.0,-6.4,0.0],"scale":[4.0,4.0,4.0]}}}