{"textures":{"0":"modelengine:entity/pursued"},"elements":[{"from":[5.714286,8.0,6.285714],"to":[10.285714,14.857143,9.714286],"rotation":{"angle":0.0,"axis":"y","origin":[8.0,8.0,8.0]},"faces":{"east":{"uv":[12.75,13.0,14.25,16.0],"rotation":0,"texture":"#0","tintindex":0},"south":{"uv":[14.0,13.0,16.0,16.0],"rotation":0,"texture":"#0","tintindex":0},"north":{"uv":[11.0,13.0,13.0,16.0],"rotation":0,"texture":"#0","tintindex":0},"west":{"uv":[12.75,13.0,14.25,16.0],"rotation":0,"texture":"#0","tintindex":0},"up":{"uv":[11.0,11.75,13.0,13.25],"rotation":0,"texture":"#0","tintindex":0},"down":{"uv":[14.0,11.5,16.0,13.0],"rotation":0,"texture":"#0","tintindex":0}}}],"display":{"head":{"translation":[0.0,-6.4,0.0],"scale":[4.0,4.0,4.0]}}}